fs/imapfs.py
fs.imapfs-0.2.2.dist-info/LICENSE
fs.imapfs-0.2.2.dist-info/METADATA
fs.imapfs-0.2.2.dist-info/WHEEL
fs.imapfs-0.2.2.dist-info/top_level.txt
fs.imapfs-0.2.2.dist-info/zip-safe
fs.imapfs-0.2.2.dist-info/RECORD
