Metadata-Version: 2.1
Name: fs.imapfs
Version: 0.2.2
Summary: Pyfilesystem2 implementation for Imap
Home-page: http://github.com/Maggi-Andrea/fs.imapfs
Author: Andrea Maggi
Author-email: andrea@maggicontrols.com
License: MIT
Keywords: filesystem,Pyfilesystem2,imap
Platform: any
Classifier: Development Status :: 3 - Alpha
Classifier: Intended Audience :: Developers
Classifier: License :: OSI Approved :: GNU Lesser General Public License v2 or later (LGPLv2+)
Classifier: Operating System :: OS Independent
Classifier: Programming Language :: Python
Classifier: Programming Language :: Python :: 2.7
Classifier: Programming Language :: Python :: 3.5
Classifier: Programming Language :: Python :: 3.6
Classifier: Programming Language :: Python :: 3.7
Classifier: Programming Language :: Python :: 3.8
Classifier: Programming Language :: Python :: 3.9
Classifier: Programming Language :: Python :: 3.10
Classifier: Topic :: Internet
Classifier: Topic :: Security
Classifier: Topic :: Software Development :: Libraries :: Python Modules
Classifier: Topic :: System :: Filesystems
Requires-Python: !=3.0.*,!=3.1.*,!=3.2.*,!=3.3.*,>=2.7
License-File: LICENSE
Requires-Dist: fs ==2.4.16
Requires-Dist: IMAPClient
Requires-Dist: importlib-metadata
